{
  "menu": [
    {
      "img": "img/tabs/vegy.jpg",
      "altimg": "vegy",
      "title": "Меню 'Фитнес'",
      "descr": "Меню 'Фитнес' - это новый подход к приготовлению блюд: больше свежих овощей и фруктов. Продукт активных и здоровых людей. Это абсолютно новый продукт с оптимальной ценой и высоким качеством!",
      "price": 9
    },
    {
      "img": "img/tabs/post.jpg",
      "altimg": "post",
      "title": "Меню 'Постное'",
      "descr": "Меню 'Постное' - это тщательный подбор ингредиентов: полное отсутствие продуктов животного происхождения, молоко из миндаля, овса, кокоса или гречки, правильное количество белков за счет тофу и импортных вегетарианских стейков.",
      "price": 14
    },
    {
      "img": "img/tabs/elite.jpg",
      "altimg": "elite",
      "title": "Меню 'Премиум'",
      "descr": "В меню 'Премиум' мы используем не только красивый дизайн упаковки, но и качественное исполнение блюд. Красная рыба, морепродукты, фрукты - ресторанное меню без похода в ресторан!",
      "price": 21
    }
  ],
  "requests": [
    {
      "name": "json",
      "phone": "66666666",
      "id": 1
    },
    {
      "name": "esfdf",
      "phone": "546567",
      "id": 2
    },
    {
      "name": "dfsd",
      "phone": "475457",
      "id": 3
    },
    {
      "name": "cd",
      "phone": "56",
      "id": 4
    },
    {
      "name": "sgre",
      "phone": "456456",
      "id": 5
    },
    {
      "name": "fsgr",
      "phone": "666666",
      "id": 6
    },
    {
      "name": "dfgdg",
      "phone": "5566",
      "id": 7
    },
    {
      "name": "fgsfg",
      "phone": "sfbfb",
      "id": 8
    },
    {
      "name": "fxb",
      "phone": "4345",
      "id": 9
    }
  ]
}